img2tensor/__init__.py
img2tensor/core.py
img2tensor-0.1.4.dist-info/licenses/LICENSE
img2tensor-0.1.4.dist-info/METADATA
img2tensor-0.1.4.dist-info/WHEEL
img2tensor-0.1.4.dist-info/top_level.txt
img2tensor-0.1.4.dist-info/RECORD
