Metadata-Version: 2.4
Name: img2tensor
Version: 0.1.4
Summary: Unified image to tensor utility with streaming TFRecord support
Author: Sourabh Yadav
Project-URL: Homepage, https://github.com/sourabhyadav999/img2tensor
Classifier: Programming Language :: Python :: 3
Classifier: License :: OSI Approved :: MIT License
Classifier: Operating System :: OS Independent
Classifier: Topic :: Scientific/Engineering :: Artificial Intelligence
Requires-Python: >=3.8
License-File: LICENSE
Requires-Dist: numpy
Requires-Dist: pillow
Requires-Dist: pqdm
Requires-Dist: opencv-python-headless
Provides-Extra: torch
Requires-Dist: torch; extra == "torch"
Requires-Dist: torchvision; extra == "torch"
Provides-Extra: tf
Requires-Dist: tensorflow; extra == "tf"
Provides-Extra: all
Requires-Dist: torch; extra == "all"
Requires-Dist: torchvision; extra == "all"
Requires-Dist: tensorflow; extra == "all"
Dynamic: license-file
